graphene_permissions/__init__.py
graphene_permissions/mixins.py
graphene_permissions/permissions.py
graphene_permissions-1.1.4.dist-info/LICENSE.txt
graphene_permissions-1.1.4.dist-info/METADATA
graphene_permissions-1.1.4.dist-info/WHEEL
graphene_permissions-1.1.4.dist-info/top_level.txt
graphene_permissions-1.1.4.dist-info/RECORD
