Metadata-Version: 2.1
Name: graphene-permissions
Version: 1.1.4
Summary: Simple graphene-django permission system.
Home-page: https://github.com/redzej/graphene-permissions
Author: redzej
License: MIT
Keywords: graphene django permissions permission system
Platform: UNKNOWN
Classifier: Development Status :: 5 - Production/Stable
Classifier: Operating System :: OS Independent
Classifier: Programming Language :: Python :: 3
Classifier: Programming Language :: Python :: 3.5
Classifier: Programming Language :: Python :: 3.6
Classifier: Programming Language :: Python :: 3.8
Classifier: Environment :: Web Environment
Classifier: Framework :: Django :: 2.0
Classifier: Framework :: Django :: 3.0
Classifier: Topic :: Internet :: WWW/HTTP
Classifier: Intended Audience :: Developers
Requires-Python: >=3.5
Requires-Dist: django-filter
Requires-Dist: graphene
Requires-Dist: graphene-django
